ShipthisAPI/__init__.py
ShipthisAPI/shipthisapi.py
shipthisapi_python-1.2.0.dist-info/METADATA
shipthisapi_python-1.2.0.dist-info/WHEEL
shipthisapi_python-1.2.0.dist-info/entry_points.txt
shipthisapi_python-1.2.0.dist-info/top_level.txt
shipthisapi_python-1.2.0.dist-info/RECORD
