Metadata-Version: 2.1
Name: shipthisapi-python
Version: 1.2.0
Summary: ShipthisAPI utility package
Home-page: https://github.com/shipthisco/shipthisapi-python
Author: Mayur Rawte
Author-email: mayur@shipthis.co
License: UNKNOWN
Platform: UNKNOWN
Classifier: Programming Language :: Python :: 3
Classifier: License :: OSI Approved :: MIT License
Classifier: Operating System :: OS Independent
